bugzilla/__init__.py
bugzilla/_authfiles.py
bugzilla/_backendbase.py
bugzilla/_backendrest.py
bugzilla/_backendxmlrpc.py
bugzilla/_cli.py
bugzilla/_rhconverters.py
bugzilla/_session.py
bugzilla/_util.py
bugzilla/apiversion.py
bugzilla/base.py
bugzilla/bug.py
bugzilla/exceptions.py
bugzilla/oldclasses.py
bugzilla/rhbugzilla.py
python_bugzilla_anolis-0.0.1.data/data/share/man/man1/bugzilla.1
python_bugzilla_anolis-0.0.1.dist-info/COPYING
python_bugzilla_anolis-0.0.1.dist-info/METADATA
python_bugzilla_anolis-0.0.1.dist-info/WHEEL
python_bugzilla_anolis-0.0.1.dist-info/entry_points.txt
python_bugzilla_anolis-0.0.1.dist-info/top_level.txt
python_bugzilla_anolis-0.0.1.dist-info/RECORD
